Workbook

Sheet 100% Insp
A2: Police Officers: JAMES HALL JENNINGS STEPHENS ADAMS Date: __05_ / SEPT/ 25 /
A4: Put a line through police officer(s) name(s) that are not on duty (Example: Fenn) | J4: K-9 Officer(s) present
A6: 100 % Inspection of Commercial Vehicle (Open hood, all exterior doors, compartments, interior compartments, storage boxes)
A7: # | B7: Time | C7: Driver Name | F7: Company Name | J7: Vehicle Registration or Tag # | M7: State
C9: Driver License Number & State | F9: Phone Number | J9: Vehicle VIN #
A11: Driver's Home Address with City & State | F11: Company Address with City & State | J11: Make | K11: Model | L11: Color | M11: Destination
A14: Gender | C14: Race | D14: Height | E14: Weight | F14: Trailer Type (Flat, Box, Dump, Liquid) | J14: TLR Tag # | K14: State | L14: Seal (Y/N) | M14: Seal #
F15: □ Flat | G15: □Dump | H15: □Liquid | I15: □Box
A16: Contraband Found (Yes/No) | E16: Contraband Type | L16: Citation issued
A17: □ Yes □ No | E17: □Pistol □ Rifle □Knife (3" or more) □ Narcotics/Drugs/Pills | L17: □ Yes □ No
E18: □OC Spray □ Billy Club □Stun Gun/Taser □ Explosives
A19: # | B19: Time | C19: Driver Name | F19: Company Name | J19: Vehicle Registration or Tag # | M19: State
C21: Driver License Number & State | F21: Phone Number | J21: Vehicle VIN #
A23: Driver's Home Address with City & State | F23: Company Address with City & State | J23: Make | K23: Model | L23: Color | M23: Destination
A26: Gender | C26: Race | D26: Height | E26: Weight | F26: Trailer Type (Flat, Box, Dump, Liquid) | J26: TLR Tag # | K26: State | L26: Seal (Y/N) | M26: Seal #
F27: □ Flat | G27: □Dump | H27: □Liquid | I27: □Box
A28: Contraband Found (Yes/No) | E28: Contraband Type | L28: Citation issued
A29: □ Yes □ No | E29: □Pistol □ Rifle □Knife (3" or more) □ Narcotics/Drugs/Pills | L29: □ Yes □ No
E30: □OC Spray □ Billy Club □Stun Gun/Taser □ Explosives
A32: Police Officers: JAMES HALL JENNINGS STEPHENS ADAMS Date: __05_ / SEPT/ 25 /
A34: Put a line through police officer(s) name(s) that are not on duty (Example: Fenn) | J34: K-9 Officer(s) present
A36: 100 % Inspection of Commercial Vehicle (Open hood, all exterior doors, compartments, interior compartments, storage boxes)
A37: # | B37: Time | C37: Driver Name | F37: Company Name | J37: Vehicle Registration or Tag # | M37: State
C39: Driver License Number & State | F39: Phone Number | J39: Vehicle VIN #
A41: Driver's Home Address with City & State | F41: Company Address with City & State | J41: Make | K41: Model | L41: Color | M41: Destination
A44: Gender | C44: Race | D44: Height | E44: Weight | F44: Trailer Type (Flat, Box, Dump, Liquid) | J44: TLR Tag # | K44: State | L44: Seal (Y/N) | M44: Seal #
F45: □ Flat | G45: □Dump | H45: □Liquid | I45: □Box
A46: Contraband Found (Yes/No) | E46: Contraband Type | L46: Citation issued
A47: □ Yes □ No | E47: □Pistol □ Rifle □Knife (3" or more) □ Narcotics/Drugs/Pills | L47: □ Yes □ No
E48: □OC Spray □ Billy Club □Stun Gun/Taser □ Explosives
A49: # | B49: Time | C49: Driver Name | F49: Company Name | J49: Vehicle Registration or Tag # | M49: State
C51: Driver License Number & State | F51: Phone Number | J51: Vehicle VIN #
A53: Driver's Home Address with City & State | F53: Company Address with City & State | J53: Make | K53: Model | L53: Color | M53: Destination
A56: Gender | C56: Race | D56: Height | E56: Weight | F56: Trailer Type (Flat, Box, Dump, Liquid) | J56: TLR Tag # | K56: State | L56: Seal (Y/N) | M56: Seal #
F57: □ Flat | G57: □Dump | H57: □Liquid | I57: □Box
A58: Contraband Found (Yes/No) | E58: Contraband Type | L58: Citation issued
A59: □ Yes □ No | E59: □Pistol □ Rifle □Knife (3" or more) □ Narcotics/Drugs/Pills | L59: □ Yes □ No
E60: □OC Spray □ Billy Club □Stun Gun/Taser □ Explosives

Sheet Normal Ops (Comm Veh.) (2)
F1: Inspectors:
F2: Ofc James | H2: Lt Qualls | J2: Ofc Hall | W2: Date: | X2: 46080
F3: Lt Qualls | H3: LCPL BLAIR
N5: K-9/Police present: | P5: NONE
F7: Driver Name | I7: Company Name | M7: Type | O7: Vehicle Registration, State | W7: Number of | X7: Return | Y7: JOE PERRY | AB7: =IFERROR(VLOOKUP(L7,'[1]DATA BASE'!I:Q,3,FALSE),"") | AE7: =IFERROR(VLOOKUP(L7,'[1]DATA BASE'!I:Q,9,FALSE),"") | AG7: =IFERROR(VLOOKUP(L7,'[1]DATA BASE'!I:Q,6,FALSE),"") | AJ7: =VLOOKUP(L7,'[1]DATA BASE'!I:Q,8,FALSE)
A8: # | B8: G, F, R | C8: Occupants | D8: LG/SM | E8: Time | F8: Driver License Number & State | I8: Phone Number | M8: (Circle the type of trailer) | O8: Make, Model, Color | U8: Destination | W8: Returns | X8: Occupants | Y8: =VLOOKUP(L7,'DATA BASE'!B:B,Y9,FALSE) | AB8: =IFERROR(VLOOKUP(L7,'[1]DATA BASE'!I:Q,4,FALSE),"") | AE8: =IFERROR(VLOOKUP(L7,'[1]DATA BASE'!I:Q,5,FALSE),"") | AG8: =IFERROR(VLOOKUP(L7,'[1]DATA BASE'!I:Q,7,FALSE),"")
A9: 1 | B9: G | C9: 2 | D9: LG | E9: *0700 | F9: JOSUHA AMMOS | I9: OXFORD | M9: CONTRACTOR | O9: JN2Y98 GA | U9: GATE 5 | W9: 1 | Y9: DAVID WILDNER | AB9: =IFERROR(VLOOKUP(F9,'DATA BASE'!A:I,3,FALSE),"") | AE9: =IFERROR(VLOOKUP(F9,'DATA BASE'!A:I,9,FALSE),"") | AG9: =IFERROR(VLOOKUP(F9,'DATA BASE'!A:I,6,FALSE),"") | AJ9: =IFERROR(VLOOKUP(F9,'DATA BASE'!A:I,8,FALSE),"")
F10: 070519264 GA | I10: 2294073239 | M10: DUMP | O10: WHITE INTERNATIONAL | Y10: =VLOOKUP(F9,'DATA BASE'!A:I,2,FALSE) | AB10: =IFERROR(VLOOKUP(F9,'DATA BASE'!A:I,4,FALSE),"") | AE10: =IFERROR(VLOOKUP(F9,'DATA BASE'!A:I,5,FALSE),"") | AG10: =IFERROR(VLOOKUP(F9,'DATA BASE'!A:I,7,FALSE),"")
A11: 2 | B11: G | C11: 3 | D11: SM | E11: *0702 | F11: WILLIAMS AARON | I11: OXFORD | M11: CONTRACTOR | O11: SDL8511 GA | U11: GATE 5 | Y11: DAVID WILDNER | AB11: =IFERROR(VLOOKUP(F11,'DATA BASE'!A:I,3,FALSE),"") | AE11: =IFERROR(VLOOKUP(F11,'DATA BASE'!A:I,9,FALSE),"") | AG11: =IFERROR(VLOOKUP(F11,'DATA BASE'!A:I,6,FALSE),"") | AJ11: =IFERROR(VLOOKUP(F11,'DATA BASE'!A:I,8,FALSE),"")
F12: 055944423 GA | I12: 2294073239 | M12: PU | O12: GREEN FORD | Y12: =VLOOKUP(F11,'DATA BASE'!A:I,2,FALSE) | AB12: =IFERROR(VLOOKUP(F11,'DATA BASE'!A:I,4,FALSE),"") | AE12: =IFERROR(VLOOKUP(F11,'DATA BASE'!A:I,5,FALSE),"") | AG12: =IFERROR(VLOOKUP(F11,'DATA BASE'!A:I,7,FALSE),"")
A13: 3 | B13: G | C13: 3 | D13: SM | E13: *0703 | F13: GREG BROCK | I13: TASTY KAKE | M13: COMMERCIAL | O13: GBW501 GA | U13: BASEWIDE | Y13: DAVID WILDNER | AB13: =IFERROR(VLOOKUP(F13,'DATA BASE'!A:I,3,FALSE),"") | AE13: =IFERROR(VLOOKUP(F13,'DATA BASE'!A:I,9,FALSE),"") | AG13: =IFERROR(VLOOKUP(F13,'DATA BASE'!A:I,6,FALSE),"") | AJ13: =IFERROR(VLOOKUP(F13,'DATA BASE'!A:I,8,FALSE),"")
F14: *054614269 GA | I14: 2298547008 | M14: SEMI BOX | O14: FREIGHTLINER, WHITE | Y14: =VLOOKUP(F13,'DATA BASE'!A:I,2,FALSE) | AB14: =IFERROR(VLOOKUP(F13,'DATA BASE'!A:I,4,FALSE),"") | AE14: =IFERROR(VLOOKUP(F13,'DATA BASE'!A:I,5,FALSE),"") | AG14: =IFERROR(VLOOKUP(F13,'DATA BASE'!A:I,7,FALSE),"")
A15: 4 | B15: G | C15: 1 | D15: SM | E15: *0705 | F15: JOSEPH PERRY | I15: EMCO SERVICES | M15: CONTRACTOR | O15: PXQK65 FL | U15: BASEWIDE | W15: 3 | Y15: DAVID WILDNER | AB15: =IFERROR(VLOOKUP(F15,'DATA BASE'!A:I,3,FALSE),"") | AE15: =IFERROR(VLOOKUP(F15,'DATA BASE'!A:I,9,FALSE),"") | AG15: =IFERROR(VLOOKUP(F15,'DATA BASE'!A:I,6,FALSE),"") | AJ15: =IFERROR(VLOOKUP(F15,'DATA BASE'!A:I,8,FALSE),"")
F16: *049722562 GA | I16: 2298696940 | M16: VAN | O16: FORD, WHITE | Y16: =VLOOKUP(F15,'DATA BASE'!A:I,2,FALSE) | AB16: =IFERROR(VLOOKUP(F15,'DATA BASE'!A:I,4,FALSE),"") | AE16: =IFERROR(VLOOKUP(F15,'DATA BASE'!A:I,5,FALSE),"") | AG16: =IFERROR(VLOOKUP(F15,'DATA BASE'!A:I,7,FALSE),"")
A17: 5 | B17: G | C17: 1 | D17: LG | E17: *0709 | F17: DZHUMANOV BOZULAN | I17: NEW TRANS | M17: COMMERCIAL | O17: P1302270 IL | U17: 1221 | Y17: DAVID WILDNER | AB17: =IFERROR(VLOOKUP(F17,'DATA BASE'!A:I,3,FALSE),"") | AE17: =IFERROR(VLOOKUP(F17,'DATA BASE'!A:I,9,FALSE),"") | AG17: =IFERROR(VLOOKUP(F17,'DATA BASE'!A:I,6,FALSE),"") | AJ17: =IFERROR(VLOOKUP(F17,'DATA BASE'!A:I,8,FALSE),"")
F18: Y7912677 CA | I18: 6699462830 | M18: FLAT | O18: BLUE VOLVO | Y18: =VLOOKUP(F17,'DATA BASE'!A:I,2,FALSE) | AB18: =IFERROR(VLOOKUP(F17,'DATA BASE'!A:I,4,FALSE),"") | AE18: =IFERROR(VLOOKUP(F17,'DATA BASE'!A:I,5,FALSE),"") | AG18: =IFERROR(VLOOKUP(F17,'DATA BASE'!A:I,7,FALSE),"")
A19: 6 | B19: F | C19: 1 | D19: LG | E19: *0710 | F19: NATHAN WOODS | I19: COCA COLA | M19: COMMERCIAL | O19: P683CL GA | U19: 7450 | Y19: DAVID WILDNER | AB19: =IFERROR(VLOOKUP(F19,'DATA BASE'!A:I,3,FALSE),"") | AE19: =IFERROR(VLOOKUP(F19,'DATA BASE'!A:I,9,FALSE),"") | AG19: =IFERROR(VLOOKUP(F19,'DATA BASE'!A:I,6,FALSE),"") | AJ19: =IFERROR(VLOOKUP(F19,'DATA BASE'!A:I,8,FALSE),"")
F20: *061070163 GA | I20: 2294720465 | M20: BOX | O20: RED INTERNATIONAL | Y20: =VLOOKUP(F19,'DATA BASE'!A:I,2,FALSE) | AB20: =IFERROR(VLOOKUP(F19,'DATA BASE'!A:I,4,FALSE),"") | AE20: =IFERROR(VLOOKUP(F19,'DATA BASE'!A:I,5,FALSE),"") | AG20: =IFERROR(VLOOKUP(F19,'DATA BASE'!A:I,7,FALSE),"")
A21: 7 | B21: G | C21: 1 | D21: SM | E21: *0712 | F21: THOMAS CAMP | I21: GTPC | M21: CONTRACTOR | O21: 6EH0777 MD | U21: BASEWIDE | Y21: DAVID WILDNER | AB21: =IFERROR(VLOOKUP(F21,'DATA BASE'!A:I,3,FALSE),"") | AE21: =IFERROR(VLOOKUP(F21,'DATA BASE'!A:I,9,FALSE),"") | AG21: =IFERROR(VLOOKUP(F21,'DATA BASE'!A:I,6,FALSE),"") | AJ21: =IFERROR(VLOOKUP(F21,'DATA BASE'!A:I,8,FALSE),"")
F22: *052037364 GA | I22: 8009490223 | M22: PU | O22: CHEVY, WHITE | Y22: =VLOOKUP(F21,'DATA BASE'!A:I,2,FALSE) | AB22: =IFERROR(VLOOKUP(F21,'DATA BASE'!A:I,4,FALSE),"") | AE22: =IFERROR(VLOOKUP(F21,'DATA BASE'!A:I,5,FALSE),"") | AG22: =IFERROR(VLOOKUP(F21,'DATA BASE'!A:I,7,FALSE),"")
A23: 8 | B23: G | C23: 1 | D23: SM | E23: *0713 | F23: DONNIE BURLSON | I23: ACE TECH | M23: CONTRACTOR | O23: DAT4681 GA | U23: BASEWIDE | W23: 2 | Y23: DAVID WILDNER | AB23: =IFERROR(VLOOKUP(F23,'DATA BASE'!A:I,3,FALSE),"") | AE23: =IFERROR(VLOOKUP(F23,'DATA BASE'!A:I,9,FALSE),"") | AG23: =IFERROR(VLOOKUP(F23,'DATA BASE'!A:I,6,FALSE),"") | AJ23: =IFERROR(VLOOKUP(F23,'DATA BASE'!A:I,8,FALSE),"")
F24: *053671480 GA | I24: 2292446412 | M24: PU | O24: RED FORD | Y24: =VLOOKUP(F23,'DATA BASE'!A:I,2,FALSE) | AB24: =IFERROR(VLOOKUP(F23,'DATA BASE'!A:I,4,FALSE),"") | AE24: =IFERROR(VLOOKUP(F23,'DATA BASE'!A:I,5,FALSE),"") | AG24: =IFERROR(VLOOKUP(F23,'DATA BASE'!A:I,7,FALSE),"")
A25: 9 | B25: G | C25: 1 | D25: SM | E25: *0741 | F25: JAMES ROWE | I25: ACE TECH | M25: CONTRACTOR | O25: DAT4680 GA | U25: BASEWIDE | Y25: DAVID WILDNER | AB25: =IFERROR(VLOOKUP(F25,'DATA BASE'!A:I,3,FALSE),"") | AE25: =IFERROR(VLOOKUP(F25,'DATA BASE'!A:I,9,FALSE),"") | AG25: =IFERROR(VLOOKUP(F25,'DATA BASE'!A:I,6,FALSE),"") | AJ25: =IFERROR(VLOOKUP(F25,'DATA BASE'!A:I,8,FALSE),"")
F26: *053081838 GA | I26: 2292446412 | M26: PU | O26: RED FORD | Y26: =VLOOKUP(F25,'DATA BASE'!A:I,2,FALSE) | AB26: =IFERROR(VLOOKUP(F25,'DATA BASE'!A:I,4,FALSE),"") | AE26: =IFERROR(VLOOKUP(F25,'DATA BASE'!A:I,5,FALSE),"") | AG26: =IFERROR(VLOOKUP(F25,'DATA BASE'!A:I,7,FALSE),"")
A27: 10 | B27: G | C27: 2 | D27: LG | E27: *0748 | F27: CALEB CROSBY | I27: RYDER | M27: COMMERCIAL | O27: 2833418 IN | U27: 1260 | Y27: DAVID WILDNER | AB27: =IFERROR(VLOOKUP(F27,'DATA BASE'!A:I,3,FALSE),"") | AE27: =IFERROR(VLOOKUP(F27,'DATA BASE'!A:I,9,FALSE),"") | AG27: =IFERROR(VLOOKUP(F27,'DATA BASE'!A:I,6,FALSE),"") | AJ27: =IFERROR(VLOOKUP(F27,'DATA BASE'!A:I,8,FALSE),"")
F28: 9426017 AL | I28: 3342968917 | M28: BOX | O28: WHITE INTERNATIONAL | Y28: =VLOOKUP(F27,'DATA BASE'!A:I,2,FALSE) | AB28: =IFERROR(VLOOKUP(F27,'DATA BASE'!A:I,4,FALSE),"") | AE28: =IFERROR(VLOOKUP(F27,'DATA BASE'!A:I,5,FALSE),"") | AG28: =IFERROR(VLOOKUP(F27,'DATA BASE'!A:I,7,FALSE),"")
A29: 11 | B29: G | C29: 1 | D29: LG | E29: *0751 | F29: WILLIAM PROCTOR | I29: YK EXPRESS | M29: COMMERICAL | O29: XE821S FL | U29: 1221 | Y29: DAVID WILDNER | AB29: =IFERROR(VLOOKUP(F29,'DATA BASE'!A:I,3,FALSE),"") | AE29: =IFERROR(VLOOKUP(F29,'DATA BASE'!A:I,9,FALSE),"") | AG29: =IFERROR(VLOOKUP(F29,'DATA BASE'!A:I,6,FALSE),"") | AJ29: =IFERROR(VLOOKUP(F29,'DATA BASE'!A:I,8,FALSE),"")
F30: P608784099000 FL | I30: 9418304769 | M30: FLAT | O30: BLACK PETERBILT | Y30: =VLOOKUP(F29,'DATA BASE'!A:I,2,FALSE) | AB30: =IFERROR(VLOOKUP(F29,'DATA BASE'!A:I,4,FALSE),"") | AE30: =IFERROR(VLOOKUP(F29,'DATA BASE'!A:I,5,FALSE),"") | AG30: =IFERROR(VLOOKUP(F29,'DATA BASE'!A:I,7,FALSE),"")
A31: 12 | B31: F | C31: 1 | D31: LG | E31: *0753 | F31: WILLIAM COPELAND | I31: CONCRETE ENTERP | M31: COMMERCIAL | O31: GK1878 GA | U31: KENNELS | Y31: DAVID WILDNER | AB31: =IFERROR(VLOOKUP(F31,'DATA BASE'!A:I,3,FALSE),"") | AE31: =IFERROR(VLOOKUP(F31,'DATA BASE'!A:I,9,FALSE),"") | AG31: =IFERROR(VLOOKUP(F31,'DATA BASE'!A:I,6,FALSE),"") | AJ31: =IFERROR(VLOOKUP(F31,'DATA BASE'!A:I,8,FALSE),"")
F32: *055172180 GA | I32: 2298811904 | M32: CONCRETE | O32: GREEN WESTERN | Y32: =VLOOKUP(F31,'DATA BASE'!A:I,2,FALSE) | AB32: =IFERROR(VLOOKUP(F31,'DATA BASE'!A:I,4,FALSE),"") | AE32: =IFERROR(VLOOKUP(F31,'DATA BASE'!A:I,5,FALSE),"") | AG32: =IFERROR(VLOOKUP(F31,'DATA BASE'!A:I,7,FALSE),"")
A33: 13 | B33: G | C33: 1 | D33: LG | E33: *0754 | F33: BRYAN MICHAEL | I33: SIEMENS | M33: COMMERCIAL | O33: DR44TK FL | U33: 2200 | Y33: DAVID WILDNER | AB33: =IFERROR(VLOOKUP(F33,'DATA BASE'!A:I,3,FALSE),"") | AE33: =IFERROR(VLOOKUP(F33,'DATA BASE'!A:I,9,FALSE),"") | AG33: =IFERROR(VLOOKUP(F33,'DATA BASE'!A:I,6,FALSE),"") | AJ33: =IFERROR(VLOOKUP(F33,'DATA BASE'!A:I,8,FALSE),"")
F34: B650544873820 FL | I34: 8008920288 | M34: SUV | O34: WHITE EQUINOX | Y34: =VLOOKUP(F33,'DATA BASE'!A:I,2,FALSE) | AB34: =IFERROR(VLOOKUP(F33,'DATA BASE'!A:I,4,FALSE),"") | AE34: =IFERROR(VLOOKUP(F33,'DATA BASE'!A:I,5,FALSE),"") | AG34: =IFERROR(VLOOKUP(F33,'DATA BASE'!A:I,7,FALSE),"")
A35: 14 | B35: G | C35: 1 | D35: LG | E35: *0756 | F35: TORRANCE LAWRENCE | I35: SPARTAN NASH | M35: COMMERICAL | O35: 424423 NE | U35: 7500 | Y35: DAVID WILDNER | AB35: =IFERROR(VLOOKUP(F35,'DATA BASE'!A:I,3,FALSE),"") | AE35: =IFERROR(VLOOKUP(F35,'DATA BASE'!A:I,9,FALSE),"") | AG35: =IFERROR(VLOOKUP(F35,'DATA BASE'!A:I,6,FALSE),"") | AJ35: =IFERROR(VLOOKUP(F35,'DATA BASE'!A:I,8,FALSE),"")
F36: 072479857 GA | I36: 3345409441 | M36: BOX | O36: WHITE INTERNATIONAL | Y36: =VLOOKUP(F35,'DATA BASE'!A:I,2,FALSE) | AB36: =IFERROR(VLOOKUP(F35,'DATA BASE'!A:I,4,FALSE),"") | AE36: =IFERROR(VLOOKUP(F35,'DATA BASE'!A:I,5,FALSE),"") | AG36: =IFERROR(VLOOKUP(F35,'DATA BASE'!A:I,7,FALSE),"")
A37: 15 | B37: G | C37: 1 | D37: LG | E37: *0758 | F37: TIMOTHY WALKER | I37: EXPRESS DISPOSAL | M37: CONTRACTOR | O37: YHE502 GA | U37: BASEWIDE | Y37: DAVID WILDNER | AB37: =IFERROR(VLOOKUP(F37,'DATA BASE'!A:I,3,FALSE),"") | AE37: =IFERROR(VLOOKUP(F37,'DATA BASE'!A:I,9,FALSE),"") | AG37: =IFERROR(VLOOKUP(F37,'DATA BASE'!A:I,6,FALSE),"") | AJ37: =IFERROR(VLOOKUP(F37,'DATA BASE'!A:I,8,FALSE),"")
F38: *058791327 GA | I38: 2293524300 | M38: TANK | O38: WHITE INTER | Y38: =VLOOKUP(F37,'DATA BASE'!A:I,2,FALSE) | AB38: =IFERROR(VLOOKUP(F37,'DATA BASE'!A:I,4,FALSE),"") | AE38: =IFERROR(VLOOKUP(F37,'DATA BASE'!A:I,5,FALSE),"") | AG38: =IFERROR(VLOOKUP(F37,'DATA BASE'!A:I,7,FALSE),"")
A39: 16 | B39: G | C39: 1 | D39: LG | E39: *0803 | F39: ALVIN CONLEY | I39: DAVENPORT | M39: COMMERCIAL | O39: YDR952 GA | U39: BASEWIDE | Y39: DAVID WILDNER | AB39: =IFERROR(VLOOKUP(F39,'DATA BASE'!A:I,3,FALSE),"") | AE39: =IFERROR(VLOOKUP(F39,'DATA BASE'!A:I,9,FALSE),"") | AG39: =IFERROR(VLOOKUP(F39,'DATA BASE'!A:I,6,FALSE),"") | AJ39: =IFERROR(VLOOKUP(F39,'DATA BASE'!A:I,8,FALSE),"")
F40: *050551154 GA | I40: 2294461541 | M40: BOX | O40: ISUZU, WHITE | Y40: =VLOOKUP(F39,'DATA BASE'!A:I,2,FALSE) | AB40: =IFERROR(VLOOKUP(F39,'DATA BASE'!A:I,4,FALSE),"") | AE40: =IFERROR(VLOOKUP(F39,'DATA BASE'!A:I,5,FALSE),"") | AG40: =IFERROR(VLOOKUP(F39,'DATA BASE'!A:I,7,FALSE),"")
A41: 17 | B41: G | C41: 1 | D41: LG | E41: *0820 | F41: TYRONE PITTS | I41: KLB | M41: COMMERCIAL | O41: XE820Y FL | U41: 7500 | Y41: DAVID WILDNER | AB41: =IFERROR(VLOOKUP(F41,'DATA BASE'!A:I,3,FALSE),"") | AE41: =IFERROR(VLOOKUP(F41,'DATA BASE'!A:I,9,FALSE),"") | AG41: =IFERROR(VLOOKUP(F41,'DATA BASE'!A:I,6,FALSE),"") | AJ41: =IFERROR(VLOOKUP(F41,'DATA BASE'!A:I,8,FALSE),"")
F42: P320800774 FL | I42: 8509803664 | M42: BOX | O42: TAN PETERBILT | Y42: =VLOOKUP(F41,'DATA BASE'!A:I,2,FALSE) | AB42: =IFERROR(VLOOKUP(F41,'DATA BASE'!A:I,4,FALSE),"") | AE42: =IFERROR(VLOOKUP(F41,'DATA BASE'!A:I,5,FALSE),"") | AG42: =IFERROR(VLOOKUP(F41,'DATA BASE'!A:I,7,FALSE),"")
A43: 18 | B43: F | C43: 1 | D43: LG | E43: *0822 | F43: LC BRAY | I43: MIDSOUTH PRODUCE | M43: COMMERCIAL | O43: 3521602 IN | U43: 7501 | Y43: DAVID WILDNER | AB43: =IFERROR(VLOOKUP(F43,'DATA BASE'!A:I,3,FALSE),"") | AE43: =IFERROR(VLOOKUP(F43,'DATA BASE'!A:I,9,FALSE),"") | AG43: =IFERROR(VLOOKUP(F43,'DATA BASE'!A:I,6,FALSE),"") | AJ43: =IFERROR(VLOOKUP(F43,'DATA BASE'!A:I,8,FALSE),"")
F44: 7174932 AL | I44: 2059284536 | M44: BOX | O44: FREIGHTLINER, WHITE | Y44: =VLOOKUP(F43,'DATA BASE'!A:I,2,FALSE) | AB44: =IFERROR(VLOOKUP(F43,'DATA BASE'!A:I,4,FALSE),"") | AE44: =IFERROR(VLOOKUP(F43,'DATA BASE'!A:I,5,FALSE),"") | AG44: =IFERROR(VLOOKUP(F43,'DATA BASE'!A:I,7,FALSE),"")
A45: 19 | B45: G | C45: 1 | D45: SM | E45: *0827 | F45: BENJAMIN WALKER | I45: POOL GEEKS | M45: CONTRACTOR | O45: SGM8699 GA | U45: HOUSING | Y45: DAVID WILDNER | AB45: =IFERROR(VLOOKUP(F45,'DATA BASE'!A:I,3,FALSE),"") | AE45: =IFERROR(VLOOKUP(F45,'DATA BASE'!A:I,9,FALSE),"") | AG45: =IFERROR(VLOOKUP(F45,'DATA BASE'!A:I,6,FALSE),"") | AJ45: =IFERROR(VLOOKUP(F45,'DATA BASE'!A:I,8,FALSE),"")
F46: *057878110 GA | I46: 2294990820 | M46: PU | O46: WHITE FORD | Y46: =VLOOKUP(F45,'DATA BASE'!A:I,2,FALSE) | AB46: =IFERROR(VLOOKUP(F45,'DATA BASE'!A:I,4,FALSE),"") | AE46: =IFERROR(VLOOKUP(F45,'DATA BASE'!A:I,5,FALSE),"") | AG46: =IFERROR(VLOOKUP(F45,'DATA BASE'!A:I,7,FALSE),"")
A47: 20 | B47: G | C47: 1 | D47: SM | E47: *0836 | F47: FRANK GRIFFIN | I47: EMCO SERVICES | M47: CONTRACTOR | O47: PXQK65 FL | U47: BASEWIDE | Y47: DAVID WILDNER | AB47: =IFERROR(VLOOKUP(F47,'DATA BASE'!A:I,3,FALSE),"") | AE47: =IFERROR(VLOOKUP(F47,'DATA BASE'!A:I,9,FALSE),"") | AG47: =IFERROR(VLOOKUP(F47,'DATA BASE'!A:I,6,FALSE),"") | AJ47: =IFERROR(VLOOKUP(F47,'DATA BASE'!A:I,8,FALSE),"")
F48: *049722562 GA | I48: 8505144822 | M48: VAN | O48: FORD, WHITE | Y48: =VLOOKUP(F47,'DATA BASE'!A:I,2,FALSE) | AB48: =IFERROR(VLOOKUP(F47,'DATA BASE'!A:I,4,FALSE),"") | AE48: =IFERROR(VLOOKUP(F47,'DATA BASE'!A:I,5,FALSE),"") | AG48: =IFERROR(VLOOKUP(F47,'DATA BASE'!A:I,7,FALSE),"")
A49: 21 | B49: G | C49: 1 | D49: SM | E49: *0855 | F49: BRYAN MERRITT | I49: XTREAM | M49: CONTRACTOR | O49: CLS1409 GA | U49: HOUSING | Y49: DAVID WILDNER | AB49: =IFERROR(VLOOKUP(F49,'DATA BASE'!A:I,3,FALSE),"") | AE49: =IFERROR(VLOOKUP(F49,'DATA BASE'!A:I,9,FALSE),"") | AG49: =IFERROR(VLOOKUP(F49,'DATA BASE'!A:I,6,FALSE),"") | AJ49: =IFERROR(VLOOKUP(F49,'DATA BASE'!A:I,8,FALSE),"")
F50: 055072118 GA | I50: 2298811184 | M50: VAN | O50: WHITE FORD | Y50: =VLOOKUP(F49,'DATA BASE'!A:I,2,FALSE) | AB50: =IFERROR(VLOOKUP(F49,'DATA BASE'!A:I,4,FALSE),"") | AE50: =IFERROR(VLOOKUP(F49,'DATA BASE'!A:I,5,FALSE),"") | AG50: =IFERROR(VLOOKUP(F49,'DATA BASE'!A:I,7,FALSE),"")
A51: 22 | B51: G | C51: 1 | D51: LG | E51: *0857 | F51: BRAD STAFFORD | I51: BLUE BELL | M51: COMMERCIAL | O51: K078831 TX | U51: 7501 | Y51: DAVID WILDNER | AB51: =IFERROR(VLOOKUP(F51,'DATA BASE'!A:I,3,FALSE),"") | AE51: =IFERROR(VLOOKUP(F51,'DATA BASE'!A:I,9,FALSE),"") | AG51: =IFERROR(VLOOKUP(F51,'DATA BASE'!A:I,6,FALSE),"") | AJ51: =IFERROR(VLOOKUP(F51,'DATA BASE'!A:I,8,FALSE),"")
F52: S316076621440 FL | I52: 8505106018 | M52: BOX | O52: WHITE FL | Y52: =VLOOKUP(F51,'DATA BASE'!A:I,2,FALSE) | AB52: =IFERROR(VLOOKUP(F51,'DATA BASE'!A:I,4,FALSE),"") | AE52: =IFERROR(VLOOKUP(F51,'DATA BASE'!A:I,5,FALSE),"") | AG52: =IFERROR(VLOOKUP(F51,'DATA BASE'!A:I,7,FALSE),"")
A53: 23 | B53: G | C53: 1 | D53: SM | E53: *0923 | F53: SHANE BOYER | I53: PEPI | M53: CONTRACTOR | O53: 38A4RB3 AL | U53: 2200 | Y53: DAVID WILDNER | AB53: =IFERROR(VLOOKUP(F53,'DATA BASE'!A:I,3,FALSE),"") | AE53: =IFERROR(VLOOKUP(F53,'DATA BASE'!A:I,9,FALSE),"") | AG53: =IFERROR(VLOOKUP(F53,'DATA BASE'!A:I,6,FALSE),"") | AJ53: =IFERROR(VLOOKUP(F53,'DATA BASE'!A:I,8,FALSE),"")
F54: B238849634000 FL | I54: 4077171860 | M54: CAR | O54: WHITE FORD | Y54: =VLOOKUP(F53,'DATA BASE'!A:I,2,FALSE) | AB54: =IFERROR(VLOOKUP(F53,'DATA BASE'!A:I,4,FALSE),"") | AE54: =IFERROR(VLOOKUP(F53,'DATA BASE'!A:I,5,FALSE),"") | AG54: =IFERROR(VLOOKUP(F53,'DATA BASE'!A:I,7,FALSE),"")
A55: 24 | B55: F | C55: 1 | D55: SM | E55: *0926 | F55: COURTNEY MICHEAL | I55: LIMELIGHT | M55: CONTRACTOR | O55: JWLS41 FL | U55: GYM | Y55: DAVID WILDNER | AB55: =IFERROR(VLOOKUP(F55,'DATA BASE'!A:I,3,FALSE),"") | AE55: =IFERROR(VLOOKUP(F55,'DATA BASE'!A:I,9,FALSE),"") | AG55: =IFERROR(VLOOKUP(F55,'DATA BASE'!A:I,6,FALSE),"") | AJ55: =IFERROR(VLOOKUP(F55,'DATA BASE'!A:I,8,FALSE),"")
F56: C635557674060 FL | I56: 8505454516 | M56: PU | O56: WHITE FORD | Y56: =VLOOKUP(F55,'DATA BASE'!A:I,2,FALSE) | AB56: =IFERROR(VLOOKUP(F55,'DATA BASE'!A:I,4,FALSE),"") | AE56: =IFERROR(VLOOKUP(F55,'DATA BASE'!A:I,5,FALSE),"") | AG56: =IFERROR(VLOOKUP(F55,'DATA BASE'!A:I,7,FALSE),"")
A57: 25 | B57: G | C57: 1 | D57: SM | E57: *0936 | F57: JEFF FOWLER | I57: S&S CONCRETE | M57: CONTRACTOR | O57: TCG0009 GA | U57: 1221 | Y57: DAVID WILDNER | AB57: =IFERROR(VLOOKUP(F57,'DATA BASE'!A:I,3,FALSE),"") | AE57: =IFERROR(VLOOKUP(F57,'DATA BASE'!A:I,9,FALSE),"") | AG57: =IFERROR(VLOOKUP(F57,'DATA BASE'!A:I,6,FALSE),"") | AJ57: =IFERROR(VLOOKUP(F57,'DATA BASE'!A:I,8,FALSE),"")
F58: *054094646 GA | I58: 2294388566 | M58: PU | O58: DODGE, WHITE | Y58: =VLOOKUP(F57,'DATA BASE'!A:I,2,FALSE) | AB58: =IFERROR(VLOOKUP(F57,'DATA BASE'!A:I,4,FALSE),"") | AE58: =IFERROR(VLOOKUP(F57,'DATA BASE'!A:I,5,FALSE),"") | AG58: =IFERROR(VLOOKUP(F57,'DATA BASE'!A:I,7,FALSE),"")
A59: 26 | B59: G | C59: 1 | D59: LG | E59: *0948 | F59: KHALIF COLLIER | I59: FEDEX | M59: CONTRACTOR | O59: SPDWAGN GA | U59: BASEWIDE | Y59: DAVID WILDNER | AB59: =IFERROR(VLOOKUP(F59,'DATA BASE'!A:I,3,FALSE),"") | AE59: =IFERROR(VLOOKUP(F59,'DATA BASE'!A:I,9,FALSE),"") | AG59: =IFERROR(VLOOKUP(F59,'DATA BASE'!A:I,6,FALSE),"") | AJ59: =IFERROR(VLOOKUP(F59,'DATA BASE'!A:I,8,FALSE),"")
F60: *052140621 GA | I60: 2294180828 | M60: VAN | O60: WHITE FORD | Y60: =VLOOKUP(F59,'DATA BASE'!A:I,2,FALSE) | AB60: =IFERROR(VLOOKUP(F59,'DATA BASE'!A:I,4,FALSE),"") | AE60: =IFERROR(VLOOKUP(F59,'DATA BASE'!A:I,5,FALSE),"") | AG60: =IFERROR(VLOOKUP(F59,'DATA BASE'!A:I,7,FALSE),"")
A61: 27 | B61: G | C61: 6 | D61: LG | E61: *0952 | F61: BEANNA WARD | I61: SOUTHWEST | M61: COMMERCIAL | O61: GV0534T GA | U61: BASEWIDE | Y61: DAVID WILDNER | AB61: =IFERROR(VLOOKUP(F61,'DATA BASE'!A:I,3,FALSE),"") | AE61: =IFERROR(VLOOKUP(F61,'DATA BASE'!A:I,9,FALSE),"") | AG61: =IFERROR(VLOOKUP(F61,'DATA BASE'!A:I,6,FALSE),"") | AJ61: =IFERROR(VLOOKUP(F61,'DATA BASE'!A:I,8,FALSE),"")
F62: 050470646 GA | I62: 2297335335 | M62: VAN | O62: WHITE TRANSIT | Y62: =VLOOKUP(F61,'DATA BASE'!A:I,2,FALSE) | AB62: =IFERROR(VLOOKUP(F61,'DATA BASE'!A:I,4,FALSE),"") | AE62: =IFERROR(VLOOKUP(F61,'DATA BASE'!A:I,5,FALSE),"") | AG62: =IFERROR(VLOOKUP(F61,'DATA BASE'!A:I,7,FALSE),"")
A63: 28 | B63: G | C63: 1 | D63: LG | E63: 1022 | F63: JEREMY BONNER | I63: UPS | M63: COMMERCIAL | O63: EEP600 GA | U63: BASEWIDE | Y63: DAVID WILDNER | AB63: =IFERROR(VLOOKUP(F63,'DATA BASE'!A:I,3,FALSE),"") | AE63: =IFERROR(VLOOKUP(F63,'DATA BASE'!A:I,9,FALSE),"") | AG63: =IFERROR(VLOOKUP(F63,'DATA BASE'!A:I,6,FALSE),"") | AJ63: =IFERROR(VLOOKUP(F63,'DATA BASE'!A:I,8,FALSE),"")
F64: *056436909 GA | I64: 2292911395 | M64: VAN | O64: BROWN FREIGHTLINER | Y64: =VLOOKUP(F63,'DATA BASE'!A:I,2,FALSE) | AB64: =IFERROR(VLOOKUP(F63,'DATA BASE'!A:I,4,FALSE),"") | AE64: =IFERROR(VLOOKUP(F63,'DATA BASE'!A:I,5,FALSE),"") | AG64: =IFERROR(VLOOKUP(F63,'DATA BASE'!A:I,7,FALSE),"")
A65: 29 | B65: G | C65: 1 | D65: LG | E65: 1041 | F65: MASSEY GERALD | I65: SAUTI | M65: COMMERCIAL | O65: ZP75243 CA | U65: 1221 | Y65: DAVID WILDNER | AB65: =IFERROR(VLOOKUP(F65,'DATA BASE'!A:I,3,FALSE),"") | AE65: =IFERROR(VLOOKUP(F65,'DATA BASE'!A:I,9,FALSE),"") | AG65: =IFERROR(VLOOKUP(F65,'DATA BASE'!A:I,6,FALSE),"") | AJ65: =IFERROR(VLOOKUP(F65,'DATA BASE'!A:I,8,FALSE),"")
F66: C4267445 CA | I66: 9515073238 | M66: BOX | O66: RED KENWORTH | Y66: =VLOOKUP(F65,'DATA BASE'!A:I,2,FALSE) | AB66: =IFERROR(VLOOKUP(F65,'DATA BASE'!A:I,4,FALSE),"") | AE66: =IFERROR(VLOOKUP(F65,'DATA BASE'!A:I,5,FALSE),"") | AG66: =IFERROR(VLOOKUP(F65,'DATA BASE'!A:I,7,FALSE),"")
A67: 30 | B67: F | C67: 1 | D67: SM | E67: 1045 | F67: JOSEPH PERRY | I67: EMCO SERVICES | M67: CONTRACTOR | O67: PXQK65 FL | U67: BASEWIDE | Y67: DAVID WILDNER | AB67: =IFERROR(VLOOKUP(F67,'DATA BASE'!A:I,3,FALSE),"") | AE67: =IFERROR(VLOOKUP(F67,'DATA BASE'!A:I,9,FALSE),"") | AG67: =IFERROR(VLOOKUP(F67,'DATA BASE'!A:I,6,FALSE),"") | AJ67: =IFERROR(VLOOKUP(F67,'DATA BASE'!A:I,8,FALSE),"")
F68: *049722562 GA | I68: 2298696940 | M68: VAN | O68: FORD, WHITE | Y68: =VLOOKUP(F67,'DATA BASE'!A:I,2,FALSE) | AB68: =IFERROR(VLOOKUP(F67,'DATA BASE'!A:I,4,FALSE),"") | AE68: =IFERROR(VLOOKUP(F67,'DATA BASE'!A:I,5,FALSE),"") | AG68: =IFERROR(VLOOKUP(F67,'DATA BASE'!A:I,7,FALSE),"")
A69: 31 | B69: G | C69: 1 | D69: LG | E69: 1049 | F69: MATTHEW ROGERS | I69: FEDEX | M69: COMMERICAL | O69: 3062840 IN | U69: 1220 | Y69: DAVID WILDNER | AB69: =IFERROR(VLOOKUP(F69,'DATA BASE'!A:I,3,FALSE),"") | AE69: =IFERROR(VLOOKUP(F69,'DATA BASE'!A:I,9,FALSE),"") | AG69: =IFERROR(VLOOKUP(F69,'DATA BASE'!A:I,6,FALSE),"") | AJ69: =IFERROR(VLOOKUP(F69,'DATA BASE'!A:I,8,FALSE),"")
F70: 054163783 GA | I70: 2294496110 | M70: BOX | O70: WHITE KENWORTH | Y70: =VLOOKUP(F69,'DATA BASE'!A:I,2,FALSE) | AB70: =IFERROR(VLOOKUP(F69,'DATA BASE'!A:I,4,FALSE),"") | AE70: =IFERROR(VLOOKUP(F69,'DATA BASE'!A:I,5,FALSE),"") | AG70: =IFERROR(VLOOKUP(F69,'DATA BASE'!A:I,7,FALSE),"")
A71: 32 | B71: G | C71: 1 | D71: LG | E71: 1051 | F71: ALLEN HAMPTON | I71: 1ST COAST CARGO | M71: COMMERCIAL | O71: 3603944 IN | U71: 1221 | Y71: DAVID WILDNER | AB71: =IFERROR(VLOOKUP(F71,'DATA BASE'!A:I,3,FALSE),"") | AE71: =IFERROR(VLOOKUP(F71,'DATA BASE'!A:I,9,FALSE),"") | AG71: =IFERROR(VLOOKUP(F71,'DATA BASE'!A:I,6,FALSE),"") | AJ71: =IFERROR(VLOOKUP(F71,'DATA BASE'!A:I,8,FALSE),"")
F72: H366459920000 FL | I72: 8447312137 | M72: SEMI BOX | O72: FREIGHTLINER, WHITE | Y72: =VLOOKUP(F71,'DATA BASE'!A:I,2,FALSE) | AB72: =IFERROR(VLOOKUP(F71,'DATA BASE'!A:I,4,FALSE),"") | AE72: =IFERROR(VLOOKUP(F71,'DATA BASE'!A:I,5,FALSE),"") | AG72: =IFERROR(VLOOKUP(F71,'DATA BASE'!A:I,7,FALSE),"")
A73: 33 | B73: G | C73: 1 | D73: LG | E73: 1054 | F73: RODNEY MILES | I73: SIAI | M73: COMMERCIAL | O73: P236823 LA | U73: 1221 | Y73: DAVID WILDNER | AB73: =IFERROR(VLOOKUP(F73,'DATA BASE'!A:I,3,FALSE),"") | AE73: =IFERROR(VLOOKUP(F73,'DATA BASE'!A:I,9,FALSE),"") | AG73: =IFERROR(VLOOKUP(F73,'DATA BASE'!A:I,6,FALSE),"") | AJ73: =IFERROR(VLOOKUP(F73,'DATA BASE'!A:I,8,FALSE),"")
F74: *054562360 GA | I74: 4043540539 | M74: BOX | O74: RED VOLVO | Y74: =VLOOKUP(F73,'DATA BASE'!A:I,2,FALSE) | AB74: =IFERROR(VLOOKUP(F73,'DATA BASE'!A:I,4,FALSE),"") | AE74: =IFERROR(VLOOKUP(F73,'DATA BASE'!A:I,5,FALSE),"") | AG74: =IFERROR(VLOOKUP(F73,'DATA BASE'!A:I,7,FALSE),"")
A75: 34 | B75: G | C75: 1 | D75: LG | E75: 1056 | F75: JAVOSKI CHAMBERS | I75: FEDEX | M75: CONTRACTOR | O75: GLS248 GA | U75: BASEWIDE | Y75: DAVID WILDNER | AB75: =IFERROR(VLOOKUP(F75,'DATA BASE'!A:I,3,FALSE),"") | AE75: =IFERROR(VLOOKUP(F75,'DATA BASE'!A:I,9,FALSE),"") | AG75: =IFERROR(VLOOKUP(F75,'DATA BASE'!A:I,6,FALSE),"") | AJ75: =IFERROR(VLOOKUP(F75,'DATA BASE'!A:I,8,FALSE),"")
F76: *054288549 GA | I76: 2294858010 | M76: BOX | O76: FORD, WHITE | Y76: =VLOOKUP(F75,'DATA BASE'!A:I,2,FALSE) | AB76: =IFERROR(VLOOKUP(F75,'DATA BASE'!A:I,4,FALSE),"") | AE76: =IFERROR(VLOOKUP(F75,'DATA BASE'!A:I,5,FALSE),"") | AG76: =IFERROR(VLOOKUP(F75,'DATA BASE'!A:I,7,FALSE),"")
A77: 35 | B77: G | C77: 1 | D77: LG | E77: 1127 | F77: COMPTON ERIK | I77: FEDEX | M77: COMMERCIAL | O77: PWZ5406 OH | U77: 1221 | Y77: DAVID WILDNER | AB77: =IFERROR(VLOOKUP(F77,'DATA BASE'!A:I,3,FALSE),"") | AE77: =IFERROR(VLOOKUP(F77,'DATA BASE'!A:I,9,FALSE),"") | AG77: =IFERROR(VLOOKUP(F77,'DATA BASE'!A:I,6,FALSE),"") | AJ77: =IFERROR(VLOOKUP(F77,'DATA BASE'!A:I,8,FALSE),"")
F78: GC210924I ID | I78: 2084994232 | M78: BOX | O78: WHITE FREIGHTLINER | Y78: =VLOOKUP(F77,'DATA BASE'!A:I,2,FALSE) | AB78: =IFERROR(VLOOKUP(F77,'DATA BASE'!A:I,4,FALSE),"") | AE78: =IFERROR(VLOOKUP(F77,'DATA BASE'!A:I,5,FALSE),"") | AG78: =IFERROR(VLOOKUP(F77,'DATA BASE'!A:I,7,FALSE),"")
A79: 36 | B79: F | C79: 1 | D79: SM | E79: 1134 | F79: MARION THOMAS | I79: ESG | M79: CONTRACTOR | O79: RXL2346 GA | U79: 2200 | W79: 2 | Y79: DAVID WILDNER | AB79: =IFERROR(VLOOKUP(F79,'DATA BASE'!A:I,3,FALSE),"") | AE79: =IFERROR(VLOOKUP(F79,'DATA BASE'!A:I,9,FALSE),"") | AG79: =IFERROR(VLOOKUP(F79,'DATA BASE'!A:I,6,FALSE),"") | AJ79: =IFERROR(VLOOKUP(F79,'DATA BASE'!A:I,8,FALSE),"")
F80: *051761922 GA | I80: 2298865471 | M80: PU | O80: GREY FORD | Y80: =VLOOKUP(F79,'DATA BASE'!A:I,2,FALSE) | AB80: =IFERROR(VLOOKUP(F79,'DATA BASE'!A:I,4,FALSE),"") | AE80: =IFERROR(VLOOKUP(F79,'DATA BASE'!A:I,5,FALSE),"") | AG80: =IFERROR(VLOOKUP(F79,'DATA BASE'!A:I,7,FALSE),"")
A81: 37 | B81: G | C81: 1 | D81: LG | E81: 1148 | F81: ZION PARKS | I81: STANLEY STEAMERS | M81: CONTRACTOR | O81: SFE3959 GA | U81: HOUSING | Y81: DAVID WILDNER | AB81: =IFERROR(VLOOKUP(F81,'DATA BASE'!A:I,3,FALSE),"") | AE81: =IFERROR(VLOOKUP(F81,'DATA BASE'!A:I,9,FALSE),"") | AG81: =IFERROR(VLOOKUP(F81,'DATA BASE'!A:I,6,FALSE),"") | AJ81: =IFERROR(VLOOKUP(F81,'DATA BASE'!A:I,8,FALSE),"")
F82: *060467450 GA | I82: 2298094352 | M82: VAN | O82: YELOOW FORD | Y82: =VLOOKUP(F81,'DATA BASE'!A:I,2,FALSE) | AB82: =IFERROR(VLOOKUP(F81,'DATA BASE'!A:I,4,FALSE),"") | AE82: =IFERROR(VLOOKUP(F81,'DATA BASE'!A:I,5,FALSE),"") | AG82: =IFERROR(VLOOKUP(F81,'DATA BASE'!A:I,7,FALSE),"")
A83: 38 | B83: G | C83: 1 | D83: LG | E83: 1152 | F83: FRANK MAYS | I83: R&L | M83: COMMERCIAL | O83: 3647819 TN | U83: 1221 | Y83: DAVID WILDNER | AB83: =IFERROR(VLOOKUP(F83,'DATA BASE'!A:I,3,FALSE),"") | AE83: =IFERROR(VLOOKUP(F83,'DATA BASE'!A:I,9,FALSE),"") | AG83: =IFERROR(VLOOKUP(F83,'DATA BASE'!A:I,6,FALSE),"") | AJ83: =IFERROR(VLOOKUP(F83,'DATA BASE'!A:I,8,FALSE),"")
F84: *049093645 GA | I84: 2294498864 | M84: BOX | O84: GREEN INTER | Y84: =VLOOKUP(F83,'DATA BASE'!A:I,2,FALSE) | AB84: =IFERROR(VLOOKUP(F83,'DATA BASE'!A:I,4,FALSE),"") | AE84: =IFERROR(VLOOKUP(F83,'DATA BASE'!A:I,5,FALSE),"") | AG84: =IFERROR(VLOOKUP(F83,'DATA BASE'!A:I,7,FALSE),"")
A85: 39 | B85: G | C85: 1 | D85: LG | E85: 1155 | F85: ALPHONSO BAISDEN | I85: S&S CONCRETE | M85: CONTRACTOR | O85: GHQ358 GA | U85: 2215 | Y85: DAVID WILDNER | AB85: =IFERROR(VLOOKUP(F85,'DATA BASE'!A:I,3,FALSE),"") | AE85: =IFERROR(VLOOKUP(F85,'DATA BASE'!A:I,9,FALSE),"") | AG85: =IFERROR(VLOOKUP(F85,'DATA BASE'!A:I,6,FALSE),"") | AJ85: =IFERROR(VLOOKUP(F85,'DATA BASE'!A:I,8,FALSE),"")
F86: *054641113 GA | I86: 2298881904 | M86: DUMP | O86: WHITE FREIGHTLINER | Y86: =VLOOKUP(F85,'DATA BASE'!A:I,2,FALSE) | AB86: =IFERROR(VLOOKUP(F85,'DATA BASE'!A:I,4,FALSE),"") | AE86: =IFERROR(VLOOKUP(F85,'DATA BASE'!A:I,5,FALSE),"") | AG86: =IFERROR(VLOOKUP(F85,'DATA BASE'!A:I,7,FALSE),"")
A87: 40 | B87: G | C87: 1 | D87: LG | E87: 1157 | F87: MICHAEL WEST | I87: UNITED RENTALS | M87: COMMERCIAL | O87: 3063986 IN | U87: 7960 | Y87: DAVID WILDNER | AB87: =IFERROR(VLOOKUP(F87,'DATA BASE'!A:I,3,FALSE),"") | AE87: =IFERROR(VLOOKUP(F87,'DATA BASE'!A:I,9,FALSE),"") | AG87: =IFERROR(VLOOKUP(F87,'DATA BASE'!A:I,6,FALSE),"") | AJ87: =IFERROR(VLOOKUP(F87,'DATA BASE'!A:I,8,FALSE),"")
F88: *026122315 GA | I88: 8008773687 | M88: FLAT | O88: WHITE INTER | Y88: =VLOOKUP(F87,'DATA BASE'!A:I,2,FALSE) | AB88: =IFERROR(VLOOKUP(F87,'DATA BASE'!A:I,4,FALSE),"") | AE88: =IFERROR(VLOOKUP(F87,'DATA BASE'!A:I,5,FALSE),"") | AG88: =IFERROR(VLOOKUP(F87,'DATA BASE'!A:I,7,FALSE),"")
A89: 41 | B89: G | C89: 1 | D89: LG | E89: 1159 | F89: DAVID THOMAS | I89: SOUTH WEST TRANS | M89: COMMERCIAL | O89: GV0279L GA | U89: BASEWIDE | W89: 2 | Y89: DAVID WILDNER | AB89: =IFERROR(VLOOKUP(F89,'DATA BASE'!A:I,3,FALSE),"") | AE89: =IFERROR(VLOOKUP(F89,'DATA BASE'!A:I,9,FALSE),"") | AG89: =IFERROR(VLOOKUP(F89,'DATA BASE'!A:I,6,FALSE),"") | AJ89: =IFERROR(VLOOKUP(F89,'DATA BASE'!A:I,8,FALSE),"")
F90: *051296485 GA | I90: 6788363288 | M90: BUS | O90: WHITE FORD | Y90: =VLOOKUP(F89,'DATA BASE'!A:I,2,FALSE) | AB90: =IFERROR(VLOOKUP(F89,'DATA BASE'!A:I,4,FALSE),"") | AE90: =IFERROR(VLOOKUP(F89,'DATA BASE'!A:I,5,FALSE),"") | AG90: =IFERROR(VLOOKUP(F89,'DATA BASE'!A:I,7,FALSE),"")
A91: 42 | B91: F | C91: 1 | D91: SM | E91: 1202 | F91: CHRISTOPHER YERBY | I91: DSC-EMI | M91: CONTRACTOR | O91: TAE8497 NC | U91: 3500 | Y91: DAVID WILDNER | AB91: =IFERROR(VLOOKUP(F91,'DATA BASE'!A:I,3,FALSE),"") | AE91: =IFERROR(VLOOKUP(F91,'DATA BASE'!A:I,9,FALSE),"") | AG91: =IFERROR(VLOOKUP(F91,'DATA BASE'!A:I,6,FALSE),"") | AJ91: =IFERROR(VLOOKUP(F91,'DATA BASE'!A:I,8,FALSE),"")
F92: 054298312 GA | I92: 2298691490 | M92: PU | O92: WHITE GMC | Y92: =VLOOKUP(F91,'DATA BASE'!A:I,2,FALSE) | AB92: =IFERROR(VLOOKUP(F91,'DATA BASE'!A:I,4,FALSE),"") | AE92: =IFERROR(VLOOKUP(F91,'DATA BASE'!A:I,5,FALSE),"") | AG92: =IFERROR(VLOOKUP(F91,'DATA BASE'!A:I,7,FALSE),"")
A93: 43 | B93: G | C93: 1 | D93: LG | E93: 1208 | F93: KARIE AWIL | I93: ELEVATED LOGIS | M93: COMMERCIAL | O93: R792512 TX | U93: 1221 | Y93: DAVID WILDNER | AB93: =IFERROR(VLOOKUP(F93,'DATA BASE'!A:I,3,FALSE),"") | AE93: =IFERROR(VLOOKUP(F93,'DATA BASE'!A:I,9,FALSE),"") | AG93: =IFERROR(VLOOKUP(F93,'DATA BASE'!A:I,6,FALSE),"") | AJ93: =IFERROR(VLOOKUP(F93,'DATA BASE'!A:I,8,FALSE),"")
F94: *090764837 TN | I94: 7202243333 | M94: BOX | O94: WHITE VOLVO | Y94: =VLOOKUP(F93,'DATA BASE'!A:I,2,FALSE) | AB94: =IFERROR(VLOOKUP(F93,'DATA BASE'!A:I,4,FALSE),"") | AE94: =IFERROR(VLOOKUP(F93,'DATA BASE'!A:I,5,FALSE),"") | AG94: =IFERROR(VLOOKUP(F93,'DATA BASE'!A:I,7,FALSE),"")
A95: 44 | B95: G | C95: 1 | D95: LG | E95: 1241 | F95: JESSIE SIMON | I95: SAIS | M95: COMMERCIAL | O95: P254369 LA | U95: 1221 | Y95: DAVID WILDNER | AB95: =IFERROR(VLOOKUP(F95,'DATA BASE'!A:I,3,FALSE),"") | AE95: =IFERROR(VLOOKUP(F95,'DATA BASE'!A:I,9,FALSE),"") | AG95: =IFERROR(VLOOKUP(F95,'DATA BASE'!A:I,6,FALSE),"") | AJ95: =IFERROR(VLOOKUP(F95,'DATA BASE'!A:I,8,FALSE),"")
F96: *050184398 GA | I96: 6788185204 | M96: BOX | O96: RED FREIGHTLINER | Y96: =VLOOKUP(F95,'DATA BASE'!A:I,2,FALSE) | AB96: =IFERROR(VLOOKUP(F95,'DATA BASE'!A:I,4,FALSE),"") | AE96: =IFERROR(VLOOKUP(F95,'DATA BASE'!A:I,5,FALSE),"") | AG96: =IFERROR(VLOOKUP(F95,'DATA BASE'!A:I,7,FALSE),"")
A97: 45 | B97: G | C97: 1 | D97: SM | E97: 1249 | F97: SYREETA MITCHELL | I97: DHL | M97: COMMERCIAL | O97: 3355981 IN | U97: 1221 | Y97: DAVID WILDNER | AB97: =IFERROR(VLOOKUP(F97,'DATA BASE'!A:I,3,FALSE),"") | AE97: =IFERROR(VLOOKUP(F97,'DATA BASE'!A:I,9,FALSE),"") | AG97: =IFERROR(VLOOKUP(F97,'DATA BASE'!A:I,6,FALSE),"") | AJ97: =IFERROR(VLOOKUP(F97,'DATA BASE'!A:I,8,FALSE),"")
F98: *051381745 GA | I98: 2292910094 | M98: VAN | O98: YELLOW FORD | Y98: =VLOOKUP(F97,'DATA BASE'!A:I,2,FALSE) | AB98: =IFERROR(VLOOKUP(F97,'DATA BASE'!A:I,4,FALSE),"") | AE98: =IFERROR(VLOOKUP(F97,'DATA BASE'!A:I,5,FALSE),"") | AG98: =IFERROR(VLOOKUP(F97,'DATA BASE'!A:I,7,FALSE),"")
A99: 46 | B99: G | C99: 1 | D99: LG | E99: 1315 | F99: GUERRERO VICTRO MANUEL | I99: VMG | M99: COMMERCIAL | O99: XD271X | U99: 1221 | Y99: DAVID WILDNER | AB99: =IFERROR(VLOOKUP(F99,'DATA BASE'!A:I,3,FALSE),"") | AE99: =IFERROR(VLOOKUP(F99,'DATA BASE'!A:I,9,FALSE),"") | AG99: =IFERROR(VLOOKUP(F99,'DATA BASE'!A:I,6,FALSE),"") | AJ99: =IFERROR(VLOOKUP(F99,'DATA BASE'!A:I,8,FALSE),"")
F100: G360574500000 FL | I100: 8135351372 | M100: BOX | O100: BLACK FREIGHTLINER | Y100: =VLOOKUP(F99,'DATA BASE'!A:I,2,FALSE) | AB100: =IFERROR(VLOOKUP(F99,'DATA BASE'!A:I,4,FALSE),"") | AE100: =IFERROR(VLOOKUP(F99,'DATA BASE'!A:I,5,FALSE),"") | AG100: =IFERROR(VLOOKUP(F99,'DATA BASE'!A:I,7,FALSE),"")
A101: 47 | B101: G | C101: 1 | D101: SM | E101: 1338 | F101: OSBORNE T PARIS | I101: IMS | M101: COMMERCIAL | O101: BA552167 WV | U101: 1221 | Y101: DAVID WILDNER | AB101: =IFERROR(VLOOKUP(F101,'DATA BASE'!A:I,3,FALSE),"") | AE101: =IFERROR(VLOOKUP(F101,'DATA BASE'!A:I,9,FALSE),"") | AG101: =IFERROR(VLOOKUP(F101,'DATA BASE'!A:I,6,FALSE),"") | AJ101: =IFERROR(VLOOKUP(F101,'DATA BASE'!A:I,8,FALSE),"")
F102: F429924 WV | I102: 3045820042 | M102: FLAT | O102: BROWN KENWORTH | Y102: =VLOOKUP(F101,'DATA BASE'!A:I,2,FALSE) | AB102: =IFERROR(VLOOKUP(F101,'DATA BASE'!A:I,4,FALSE),"") | AE102: =IFERROR(VLOOKUP(F101,'DATA BASE'!A:I,5,FALSE),"") | AG102: =IFERROR(VLOOKUP(F101,'DATA BASE'!A:I,7,FALSE),"")
...

Sheet DATA BASE
A1: DRIVER NAME DRIVER | B1: LICENCE NUMBER AND STATE | C1: COMPANY NAME | D1: PHONE NUMBER | E1: TYPE | F1: VEHICLE REGISTRATION, STATE | G1: MAKE MODEL COLOR | H1: DESTINATION | I1: TYPE
A11: STEPHEN COOK | B11: 051737078 GA | C11: A WEST | D11: 2298888347 | E11: PU | F11: DBF4190 GA | G11: CHEVY, WHITE | H11: BASEWIDE | I11: CONTRACTOR
A12: FRANK GRIFFIN | B12: *049722562 GA | C12: EMCO SERVICES | D12: 8505144822 | E12: VAN | F12: PXQK65 FL | G12: FORD, WHITE | H12: BASEWIDE | I12: CONTRACTOR
A13: THOMAS CAMP | B13: *052037364 GA | C13: GTPC | D13: 8009490223 | E13: PU | F13: 6EH0777 MD | G13: CHEVY, WHITE | H13: BASEWIDE | I13: CONTRACTOR
A14: CHRIS SMITH | B14: *055371195 GA | C14: S&S CONCRETE | D14: 2294388566 | E14: PU | F14: SSCRET7 GA | G14: DODGE, WHITE | H14: 1330 | I14: CONTRACTOR
A15: DONALD LOWE | B15: *052635058 GA | C15: S&S CONCRETE | D15: 2294388566 | E15: DUMP | F15: EBJ071 GA | G15: FREIGHTLINER, WHITE | H15: BASEWIDE | I15: COMMERCIAL
A16: GREG BROCK | B16: *054614269 GA | C16: TASTY KAKE | D16: 2298547008 | E16: SEMI BOX | F16: GBW501 GA | G16: FREIGHTLINER, WHITE | H16: BASEWIDE | I16: COMMERCIAL
A17: SCOTT GILMER | B17: *049894146 GA | C17: ALBANY AIR | D17: 2294360341 | E17: PU | F17: CSE7190 GA | G17: FORD, WHITE | H17: 1210 | I17: CONTRACTOR
A18: KHALIF COLLIER | B18: *052140621 GA | C18: JB MASONRY | D18: 2294180828 | E18: SUV | F18: SPDWAGN GA | G18: CHEVY, GREEN | H18: KENNELS | I18: CONTRACTOR
A19: CALVIN CATON | B19: *051354218 GA | C19: A WEST | D19: 2298888347 | E19: PU | F19: CIZ5500 GA | G19: CHEVY, WHITE | H19: BASEWIDE | I19: CONTRACTOR
A20: DAVID WIDNER | B20: *057894921 GA | C20: RHC | D20: 2294353500 | E20: PU | F20: PLX3051 GA | G20: FORD, SILVER | H20: HOUSING | I20: CONTRACTOR
A21: KELVONTE JONES | B21: *053008698 GA | C21: SPARTAN NASH | D21: 7063290642 | E21: SEMI BOX | F21: 223642 NE | G21: INTERNATIONAL, WHITE | H21: 7501 | I21: COMMERCIAL
A22: DAVID ROGERS | B22: *058937219 GA | C22: SEPTIC PLUMBING | D22: 2294325376 | E22: BOX SEMI | F22: CXD2341 GA | G22: FORD, WHITE | H22: KENNELS | I22: CONTRACTOR
A23: FRANK GRIFFIN | B23: *055499949 GA | C23: ADAMS EXTERMINATOR | D23: 2298943420 | E23: VAN | F23: RUQ7451 GA | G23: NISSAN, WHITE | H23: HOUSING | I23: CONTRACTOR
A24: WILLIAM BOREFIELD | B24: *050951758 GA | C24: ALBANY BEVERAGE | D24: 2298811092 | E24: VAN | F24: CPU1706 GA | G24: FORD, WHITE | H24: 7500 | I24: CONTRACTOR
A25: VERNON COOK | B25: *055782627 GA | C25: CONCRETE ENTERPRISE | D25: 2298881104 | E25: CEMENT | F25: GAI103 GA | G25: MACK, GREEN | H25: GOLF COURSE | I25: COMMERCIAL
A26: JEFFREY JONES | B26: *056016504 GA | C26: RHC | D26: 2298889896 | E26: PU | F26: RDQ2218 GA | G26: FORD, RED | H26: HOUSING | I26: CONTRACTOR
A27: WILLIAM SHIVER | B27: *055739155 GA | C27: GEM | D27: 2298812598 | E27: PU | F27: RJT8950 GA | G27: CHEVY, BLACK | H27: BASEWIDE | I27: CONTRACTOR
A28: ROBERT ANDREWS | B28: *007795096 GA | C28: ESTES | D28: 2298943567 | E28: SEMI BOX | F28: 3585749 IN | G28: FREIGHTLINER, YELLOW | H28: 1221 | I28: COMMERCIAL
A29: DONALD SPILLERS | B29: *051592125 GA | C29: SUNBELT | D29: 2298865406 | E29: SEMI BOX | F29: P1249373 IL | G29: FREIGHTLINER, GREEN | H29: 1221 | I29: COMMERCIAL
A30: PATRICK RICHARDSON | B30: *053987739 GA | C30: ACT | D30: 2296032516 | E30: SEMI BOX | F30: R675615 TX | G30: FREIGHTLINER, BLUE | H30: 1221 | I30: COMMERCIAL
A31: ALLEN HAMPTON | B31: H366459920000 FL | C31: 1ST COAST CARGO | D31: 8447312137 | E31: SEMI BOX | F31: 3603944 IN | G31: FREIGHTLINER, WHITE | H31: 1221 | I31: COMMERCIAL
A32: DONNIE ULMER | B32: *055999972 GA | C32: SUNBELT | D32: 2293643984 | E32: SEMI BOX | F32: P21081932 IL | G32: FREIGHTLINER, GREEN | H32: 1221 | I32: COMMERCIAL
A33: MASON PEEPLES | B33: *057537613 GA | C33: S&S CONCRETE | D33: 2294388566 | E33: PU | F33: SSCRET2 GA | G33: DODGE, WHITE | H33: BASEWIDE | I33: CONTRACTOR
A34: SHUMONICA GRAHAM | B34: *051938874 GA | C34: DHL | D34: 2294857833 | E34: VAN | F34: 48797ND GA | G34: FORD, YELLOW | H34: 1221 | I34: CONTRACTOR
A35: JEFF FOWLER | B35: *054094646 GA | C35: S&S CONCRETE | D35: 2294388566 | E35: PU | F35: TCG0009 GA | G35: DODGE, WHITE | H35: 1221 | I35: CONTRACTOR
A36: MONTAVIOUS BUCHANAN | B36: *056819454 GA | C36: BUCHANAN SECURITY | D36: 2295663392 | E36: VAN | F36: SBR9305 GA | G36: FORD, WHITE | H36: 7000 | I36: CONTRACTOR
A37: CRAIG GILLIS | B37: 5819417 AL | C37: GA POWER | D37: 4045203683 | E37: PU | F37: CSC7473 GA | G37: FORD, WHITE | H37: SOLAR PANELS | I37: CONTRACTOR
A38: COPELAND MAX | B38: *032829415 GA | C38: SAIA | D38: 2295075148 | E38: SEMI BOX | F38: P253486 LA | G38: FREIGHTLINER, RED | H38: 1221 | I38: COMMERCIAL
A39: JOHN PRICE | B39: *054307270 GA | C39: UNIFIRST | D39: 2299390536 | E39: PU | F39: EJF362 GA | I39: CONTRACTOR
A40: DARRYL SLAUGHTER | B40: *051217687 GA | C40: US FOODS | D40: 2292885451 | E40: SEMI BOX | F40: 3047668 IN | G40: FREIGHTLINER, WHITE | H40: 7501 | I40: COMMERCIAL
A41: STEVE COOK | B41: *051737078 GA | C41: A WEST | D41: 2298888347 | E41: PU | F41: DBF4190 GA | G41: CHEVY, WHITE | H41: BASEWIDE | I41: CONTRACTOR
A42: ALEJO MENDEZ | B42: *051215374 GA | C42: METRO POWER | D42: 4782448291 | E42: PU | F42: RDB6220 GA | G42: CHEVY, WHITE | H42: FIRESTATION | I42: CONTRACTOR
A43: CHAD PINTO | B43: *007414511 SC | C43: MITCHELL BROTHER | D43: 8432717308 | E43: PU | F43: P892296 SC | G43: GMC, WHITE | H43: 7360 | I43: CONTRACTOR
A44: DONALD FREY | B44: *056476644 GA | C44: S&S CONCRETE | D44: 2294388566 | E44: PU | F44: SSCRET6 GA | G44: DODGE, WHITE | H44: 7360 | I44: CONTRACTOR
A45: WILLIAM DANIEL | B45: *053918006 GA | C45: MISSION FOODS | D45: 6786728923 | E45: PU | F45: EEG625 GA | G45: DODGE, RED | H45: 7501 | I45: CONTRACTOR
A46: SAZI ERCAN | B46: *058316658 GA | C46: FAST TRANSP. | D46: 4158810909 | E46: SEMI BOX | F46: C747ES GA | G46: VOLVO, BLUE | H46: 1221 | I46: COMMERCIAL
A47: LEON CANNON | B47: 6844300 AL | C47: LANDSTAR | D47: 2052606016 | E47: SEMI BOX | F47: 3400037 IN | G47: FREIGHTLINER, YELL | H47: 1221 | I47: COMMERCIAL
A48: ALVIN CONLEY | B48: *050551154 GA | C48: DAVENPORT | D48: 2294461541 | E48: BOX | F48: YDR952 GA | G48: ISUZU, WHITE | H48: BASEWIDE | I48: COMMERCIAL
A49: LONDON FRAZIER | B49: *06084146 GA | C49: FEDEX | D49: 2292964982 | E49: BOX | F49: AR07IK FL | G49: WHITE FORD | H49: BASEWIDE | I49: CONTRACTOR
A50: VERNON JUSTICE | B50: *025595457 GA | C50: GA POWER | D50: 2296031230 | E50: PU | F50: DAFE9809 GA | G50: FORD, WHITE | H50: BASEWIDE | I50: CONTRACTOR
A51: RICHARD CASEY | B51: *056646227 GA | C51: BAS | D51: 2292917694 | E51: VAN | F51: NLLPB03 FL | G51: FORD WHITE | H51: 7501 | I51: CONTRACTOR
A52: JEFFERS DAVIS | B52: *000007052312 NC | C52: NORTHSTAR | D52: 9109907127 | E52: SEMI FLAT | F52: PWR5311 OH | G52: INTERNATIONAL, RED | H52: 1221 | I52: COMMERCIAL
A53: CALEB FARMER | B53: *053125140 GA | C53: ADVANCE SPRINKLER | D53: 2298860242 | E53: BOX | F53: TEQ0596 GA | G53: ISUZU, WHITE | H53: BASEWIDE | I53: CONTRACTOR
A54: SHAKIROR KAMIL | B54: *053036917 GA | C54: BROTHERS EXPRESS | D54: 4046424811 | E54: SEMI FLAT | F54: C099CK GA | G54: FREIGHTLINER, WHITE | H54: 1221 | I54: COMMERCIAL
A55: JEFFREY BARBER | B55: B616424524700 FL | C55: LANDSTAR | D55: 7577532916 | E55: VAN | F55: P24615 FL | G55: MERCEDES, WHITE | H55: 1221 | I55: CONTRACTOR
A56: YEMANE HENOK | B56: 25474795 TX | C56: DNM TRANSPORT | D56: 8327565929 | E56: BOX | F56: R737536 TX | G56: FORD, WHITE | H56: 1221 | I56: CONTRACTOR
A57: DAVIS ROGERS | B57: *058937219 GA | C57: SEPTIC SOLUTIONS | D57: 2294325376 | E57: BOX | F57: CXD2341 GA | G57: FREIGHTLINER, WHITE | H57: FIRESTATION | I57: COMMERCIAL
A58: MARCUS WASHINGTON | B58: *050291321 GA | C58: ESTES | D58: 2296694299 | E58: SEMI BOX | F58: 3589578 IN | G58: INTERNATIONAL, YLW | H58: 1221 | I58: COMMERCIAL
A59: JONATHAN CURRY | B59: T63446226 VA | C59: ABEL'S CONSTRUCTION | D59: 5406618430 | E59: PU | F59: UC11431 VA | G59: DODGE, WHITE | H59: HOUSING | I59: CONTRACTOR
A60: JEFFREY CREWS | B60: A61364132 VA | C60: ABEL'S CONSTRUCTION | D60: 5402260608 | E60: BOX | F60: 106817 VA | G60: FREIGHTLINER, WHITE | H60: HOUSING | I60: CONTRACTOR
A61: CHRIS PRICE | B61: 20665238 TX | C61: ROCKWILD LOGISTICS | D61: 8328461155 | E61: PU | F61: VHJ034 TX | G61: FORD, BLUE | H61: 1331 | I61: CONTRACTOR
A62: MONTAVIOUS BUCHANAN | B62: *056819454 GA | C62: BUCHANAN SECURITY | D62: 2295663392 | E62: VAN | F62: SBR9305 GA | G62: FORD, WHITE | H62: 7000 | I62: CONTRACTOR
A63: RONALD HARPER | B63: *030201472 GA | C63: ADVANCE SPRINKLER | D63: 2298860242 | E63: PU | F63: DAA7490 GA | G63: CHEVY, GRAY | H63: BASEWIDE | I63: CONTRACTOR
A64: BENJAMIN WIGGINS | B64: W2522024200 FL | C64: EHRLICH | D64: 8008176008 | E64: PU | F64: KCUG89 FL | G64: CHEVY, WHITE | H64: 7501 | I64: CONTRACTOR
A65: JAVOSKI CHAMBERS | B65: *054288549 GA | C65: FEDEX | D65: 2294858010 | E65: BOX | F65: GLS248 GA | G65: FORD, WHITE | H65: BASEWIDE | I65: CONTRACTOR
A66: BILLIE EFIK | B66: *052548123 GA | C66: LIQUID SOLUTIONS | D66: 8666947327 | E66: SEMI FLAT | F66: R152898 TX | G66: FREIGHTLINER, WHITE | H66: 7501 | I66: COMMERCIAL
A67: MICHAEL WISE | B67: *053271015 GA | C67: SAIA | D67: 2293926466 | E67: SEMI BOX | F67: P268545 LA | G67: FREIGHTLINER, RED | H67: HOUSING | I67: COMMERCIAL
A68: TRAVIS KEAVENEY | B68: *054789511 GA | C68: UNIFIRST | D68: 9122594744 | E68: BOX | F68: EJF362 GA | G68: FREIGHTLINER, WHITE | H68: 5400 | I68: CONTRACTOR
A69: WILMER FLORES | B69: *049597116 GA | C69: CENTIMARK | D69: 9013281470 | E69: PU | F69: SFD6903 GA | G69: FORD, BLUE | H69: 1231 | I69: CONTRACTOR
A70: ROBERT BUTLER | B70: *053647999 GA | C70: XTREME | D70: 8458670614 | E70: VAN | F70: TBD7384 GA | G70: FORD, WHITE | H70: 3600 | I70: CONTRACTOR
A71: MOTES THOMAS | B71: M32118981320 FL | C71: ADVANCE SPRINKLER | D71: 2298860242 | E71: PU | F71: RIY8355 GA | G71: CHEVY, WHITE | H71: 2200 | I71: CONTRACTOR
A72: JASON PARRISH | B72: *033688731 GA | C72: ARBON | D72: 2292918029 | E72: PU | F72: EHK784 GA | G72: FORD, WHITE | H72: 1340 | I72: CONTRACTOR
A73: GERALD COLEMAN | B73: *057954816 GA | C73: DHL | D73: 2295835311 | E73: SEDAN | F73: SFX7571 GA | G73: NISSAN, WHITE | H73: 1221 | I73: CONTRACTOR
A74: WILLIAM THOMAS | B74: *049377008 GA | C74: DT MILLER | D74: 7066174334 | E74: PU | F74: SAK6046 GA | G74: GMC, BLACK | H74: 5592 | I74: CONTRACTOR
A75: SAM ANDERSON | B75: *056458062 GA | C75: UPS | D75: 2292880066 | E75: VAN | F75: WEN916 GA | G75: FORD, BROWN | H75: BASEWIDE | I75: CONTRACTOR
A76: LC BRAY | B76: 7174932 AL | C76: MIDSOUTH PRODUCE | D76: 2059284536 | E76: BOX | F76: 3521602 IN | G76: FREIGHTLINER, WHITE | H76: 7501 | I76: COMMERCIAL
A77: TAURUS MCMILLAN | B77: 56370655 | C77: USIC | D77: 2292064688 | E77: PU | F77: RTLQ67 FL | G77: WHITE NISSAN | H77: SUBSTATION | I77: CONTRACTOR
A78: GUI BO | B78: L2041733039 IN | C78: BO TRANS | D78: 3146041508 | E78: SEMI BOX | F78: RDB6220 IN | G78: BLACK VOLVO | H78: 1221 | I78: COMMERCIAL
A79: JOSHUA AMUA | B79: 049205535 IN | C79: LANDSTAR | D79: 7062314177 | E79: SEMI BOX | F79: 2518552 IN | G79: YELLOW WESTERN ST | H79: 12221 | I79: COMMERCIAL
A80: DEVIN SCOTT | B80: 0506600108 GA | C80: WT MILLER | D80: 7063202171 | E80: PU | F80: GFM846 GA | G80: WHITE CHEVY | H80: 5592 | I80: CONTRACTOR
A81: LOWERY MONTGOMERY | B81: 064264621 TN | C81: SERVICE ELECTRIC | D81: 4235512102 | E81: PU | F81: 56187 TN | G81: WHITE FORD | H81: BASEWIDE | I81: CONTRACTOR
A82: BEARDEN MICHAEL | B82: 055355526 GA | C82: YANCEY RENTALS | D82: 2295832024 | E82: SEMI FLAT | F82: P4151B GA | G82: RED PETERBILT | H82: LAY DOWN | I82: CONTRACTOR
A83: HARRY MARTINEZ | B83: M635374753291 FL | C83: CVM LOGISTICS | D83: 8138028011 | E83: SEMI BOX | F83: XA901B FL | G83: FREIGHTLINER, WHITE | H83: 3700 | I83: COMMERCIAL
A84: JOSE VALDEZ | B84: V432433850081 FL | C84: F2F TRANSPORT | D84: 7087965025 | E84: SEMI BOX | F84: U3358HY TN | G84: VOLVO, BROWN | H84: 3700 | I84: COMMERCIAL
A85: RAYMOND OLSON | B85: 051977595 GA | C85: NOMADS RV | D85: 2298946232 | E85: VAN | F85: GND494 GA | G85: FREIGHT, WHITE | H85: RV PARK | I85: CONTRACTOR
A86: ERIC PAYNE | B86: 033857945 GA | C86: SPARTAN NASH | D86: 7069927883 | E86: SEMI BOX | F86: 406875 NE | G86: INTERNATIONAL, WHITE | H86: 7501 | I86: COMMERCIAL
A87: JERRY GIBSON | B87: 054444400 GA | C87: CSI | D87: 2294461401 | E87: SEMI DUMP | F87: EYL065 GA | G87: WHITE FL | H87: BASEWIDE | I87: COMMERCIAL
A88: JEFFREY SCOTT | B88: *054484244 GA | C88: ARGO | D88: 9126629437 | E88: SEMI BOX | F88: P108270 IL | G88: VOLVO WHITE | H88: 1221 | I88: COMMERCIAL
A89: JAMES SEXTON | B89: 057642832 GA | C89: SOUTHERN TREE | D89: 2293922230 | E89: DUMP | F89: GFF940 GA | G89: WHITE INTERN | H89: 10300 | I89: CONTRACTOR
A90: DEVIN STEEN | B90: *050600108 GA | C90: WT MILLER | D90: 2293142361 | E90: PU | F90: GFM846 GA | G90: WHITE CHEVY | H90: 5592 | I90: CONTRACTOR
A91: ERIC DUNDAS | B91: *059961563 GA | C91: UNITED MACHINERY | D91: 2299778643 | E91: LIFT | F91: P763CQ GA | G91: WHITE M. | H91: KENNELS | I91: CONTRACTOR
A92: KAVIN WILBURN | B92: *054296981 GA | C92: BEVERAGE SOUTH | D92: 2293644347 | E92: SEMI BOX | F92: EGK332 GA | G92: WHITE KW | H92: 7501 | I92: COMMERCIAL
A93: ANTHONY LYONS | B93: L520012863270 FL | C93: MACKLINE CONCRET | D93: 8506033548 | E93: PU | F93: 23A1R63 AL | G93: WHITE CHEVY | H93: KENNELS | I93: CONTRACTOR
A94: LEROY MCLIN | B94: 059158159 GA | C94: COCA COLA | D94: 4784917037 | E94: SEMI BOX | F94: P683CL GA | G94: RED INTERN | H94: 7501 | I94: COMMERCIAL
A95: STANTON LODER | B95: L11175339 KY | C95: AMER TRANS | D95: 2707794884 | E95: SEMI BOX | F95: A43678 KY | G95: RED VOLVO | H95: 1221 | I95: COMMERCIAL
A96: TERRANCE JOHNSON | B96: J525812793780 FL | C96: NIGHT TRAIN EXP | D96: 8635858131 | E96: SEMI BOX | F96: TO387HY TN | G96: RED KW | H96: 1221 | I96: COMMERCIAL
A97: CHRISTOPHER FULFORD | B97: F416101872870 FL | C97: MLC CONCRETE | D97: 8506856272 | E97: PU | F97: 23A2332 AL | G97: BLUE FORD | H97: KENNELS | I97: CONTRACTOR
A98: JOSE FIGUEROA | B98: F261433542410 FL | C98: CRUZ & FIGUEROA | D98: 4074702970 | E98: SEMI BOX | F98: XEB77F FL | G98: BLACK PETERBILT | H98: 1221 | I98: COMMERCIAL
A99: CURTIS WILLIAMS | B99: *053947784 GA | C99: TERRACON | D99: 7066177594 | E99: PU | F99: CNP4785 GA | G99: WHITE FORD | H99: KENNELS | I99: CONTRACTOR
A100: TEVIN DEBERRY | B100: 000039559398 NC | C100: DEBERRY TRUCKING | D100: 9109883772 | E100: BOX | F100: ZS7526 NC | G100: WHITE INTERN | H100: 7500 | I100: COMMERCIAL
A101: NELSON FRANKLIN | B101: 000000969220 NC | C101: GHOST TRUCKING | D101: 7047732034 | E101: SEMI BOX | F101: NS9674 NC | G101: WHITE KW | H101: 1221 | I101: COMMERCIAL
A102: MARK STONE | B102: 056 797889 GA | C102: CONCRETE ENTERP | D102: 2298881904 | E102: MIXER | F102: GA1104 GA | G102: WHITE FORD | H102: KENNELS | I102: CONTRACTOR
A103: JUNIOR BELVANT | B103: B222359096000 FL | C103: SHIP N GO | D103: 2395298870 | E103: SEMI BOX | F103: XE302C FL | G103: WHITE INTERN | H103: 1221 | I103: COMMERCIAL
A104: WABLAIS VIXAMAR | B104: V2568802820 FL | C104: G FORWARD INC | D104: 7544223024 | E104: SEMI BOX | F104: P1043907 IL | G104: GREEN FREIGHTLINER | H104: 1221 | I104: COMMERCIAL
A105: CHARLES MOORE | B105: 049271850 GA | C105: MCA | D105: 2293768988 | E105: PU | F105: SEJ7910 GA | G105: NISSAN WHITE | H105: 7520 | I105: CONTRACTOR
A106: DALE MAINE | B106: *054282041 GA | C106: RHC | D106: 2292884246 | E106: PU | F106: PLX3051 GA | G106: GRAY FORD | H106: HOUSING | I106: CONTRACTOR
A107: CORY REYNOLDS | B107: *071666183 GA | C107: FLINT | D107: 8634303289 | E107: PU | F107: EZP049 GA | G107: WHITE INTERN | H107: POWERWORKS | I107: CONTRACTOR
A108: ERROLL HODGE | B108: 16237954 TX | C108: TRIPLE D | D108: 9035712855 | E108: SEMI BOX | F108: M8282 NM | G108: WHITE KW | H108: 1221 | I108: COMMERCIAL
A109: COTTON REGINALD | B109: 100240370 SC | C109: MILLERS | D109: 8433316487 | E109: FLAT | F109: P763686 SC | G109: YELLOW VOLVO | H109: 1221 | I109: COMMERCIAL
...

Sheet Daily Stat Report (2)
A1: Commercial Vehicle Entrance (Gate 5/15) Daily Stat Report
B3: Line | C3: Log | F3: # of vehicles | I3: Date: | J3: 46080
B5: Line 1 | C5: Large Trucks (Semi, Dump Trucks) | G5: {=COUNTIF('Normal Ops (Comm Veh.) (2)'!D9:D410,"LG") + SUMPRODUCT(('Normal Ops (Comm Veh.) (2)'!D9:D410="LG")*IFERROR('Normal Ops (Comm Veh.) (2)'!W9:W410,0))} | I5: 1408's | J5: 0
B7: Line 2 | C7: Small Veh. (Contr.) | G7: {=COUNTIF('Normal Ops (Comm Veh.) (2)'!D9:D410,"SM") + SUMPRODUCT(('Normal Ops (Comm Veh.) (2)'!D9:D410="SM")*IFERROR('Normal Ops (Comm Veh.) (2)'!W9:W410,0))} | I7: CCN's | J7: 0
B9: Line 4 | C9: G Inspections | G9: =COUNTIF('Normal Ops (Comm Veh.) (2)'!B9:B410,"G")
B11: Line 5 | C11: F Inspections | G11: =COUNTIF('Normal Ops (Comm Veh.) (2)'!B9:B410,"F")
B13: Line 6 | C13: R Inspections | G13: =COUNTIF('Normal Ops (Comm Veh.) (2)'!B9:B410,"R")
B15: Line 7 | C15: Individual processed threw the Gate | G15: =SUM('Normal Ops (Comm Veh.) (2)'!C9:C410,'Normal Ops (Comm Veh.) (2)'!X9:X410)
B17: Line 8 | C17: Number of returns | G17: =SUM('Normal Ops (Comm Veh.) (2)'!W9:W410)
B19: 2200 | G19: Total CVs Inspected | J19: =SUM(G5,G7)
G20: (Total of lines 1+2+8)
B21: Officers on Duty :
E22: Lt Qualls | F22: LCPL BIERY | H22: CPL JOHNSON
E23: Ofc Hall | F23: Ofc James
B24: Desk Sgt on duty who received CVI totals: | G24: Sgt Lyons
C26: ** Turn in this daily stat sheet with the daily logs **

Sheet LOG DETAILS
A1: LOG DATE | B1: 2026-03-03
A3: ENTRY TIME UTC | B3: ENTRY TIME | C3: DRIVER | D3: COMPANY | E3: VEHICLE | F3: INSPECTION TYPE | G3: SCAN TOKEN | H3: NOTES
